[{
  "_id": {
    "$oid": "6828749f34375b1b21ff6ff9"
  },
  "userId": {
    "$oid": "6825ee32eed18af919a0ed64"
  },
  "service_type": {
    "$oid": "668959f11561a7b14634d6e6"
  },
  "customer_name": "test user",
  "phone_number": "0973605900",
  "email": "haudaoquang5@gmail.com",
  "address": "Lương Tài, Văn Lâm, Hưng Yên",
  "appointment_date": {
    "$date": "2025-05-18T00:00:00.000Z"
  },
  "timeslot": {
    "$oid": "68286a1d0fe24f52ff8853d4"
  },
  "order_status": "Processing",
  "pet_info": {
    "pet_name": "Mực",
    "species": "Mèo",
    "breed": "Cam",
    "age": 1,
    "weight": 2,
    "notes": "a"
  },
  "cancel_reason": "null",
  "createdAt": {
    "$date": "2025-05-17T11:35:59.398Z"
  },
  "updatedAt": {
    "$date": "2025-05-17T11:56:13.050Z"
  },
  "__v": 0
},
{
  "_id": {
    "$oid": "682874b234375b1b21ff7006"
  },
  "userId": {
    "$oid": "6825ee32eed18af919a0ed64"
  },
  "service_type": {
    "$oid": "682432ed79206bf9c099f161"
  },
  "customer_name": "Đào Quang Hậu",
  "phone_number": "0973605900",
  "email": "daoquanghau2003@gmail.com",
  "address": "Lương Tài, Văn Lâm, Hưng Yên",
  "appointment_date": {
    "$date": "2025-05-25T00:00:00.000Z"
  },
  "timeslot": {
    "$oid": "68286a260fe24f52ff8853d7"
  },
  "order_status": "Cancel",
  "pet_info": {
    "pet_name": "Mực 1",
    "species": "Chó",
    "breed": "Lai",
    "age": 1,
    "weight": 1,
    "notes": ""
  },
  "cancel_reason": "tôi bận",
  "createdAt": {
    "$date": "2025-05-17T11:36:18.519Z"
  },
  "updatedAt": {
    "$date": "2025-05-17T11:56:51.427Z"
  },
  "__v": 0
},
{
  "_id": {
    "$oid": "682875c787d59b59c0d10a70"
  },
  "userId": {
    "$oid": "6825ee32eed18af919a0ed64"
  },
  "service_type": {
    "$oid": "668959f11561a7b14634d6e6"
  },
  "customer_name": "Đào Quang Hậu",
  "phone_number": "0973605900",
  "email": "daoquanghau2003@gmail.com",
  "address": "Số 55, ngõ 132 Nguyên Xá",
  "appointment_date": {
    "$date": "2025-05-17T00:00:00.000Z"
  },
  "timeslot": {
    "$oid": "68286a1d0fe24f52ff8853d4"
  },
  "order_status": "Cancel",
  "pet_info": {
    "pet_name": "Mực",
    "species": "Mèo",
    "breed": "Cam",
    "age": 1,
    "weight": 2,
    "notes": "a"
  },
  "cancel_reason": "null",
  "createdAt": {
    "$date": "2025-05-17T11:40:55.989Z"
  },
  "updatedAt": {
    "$date": "2025-05-17T11:56:11.315Z"
  },
  "__v": 0
},
{
  "_id": {
    "$oid": "682879951a7412368ad1efad"
  },
  "userId": {
    "$oid": "6825ee32eed18af919a0ed64"
  },
  "service_type": {
    "$oid": "668959f11561a7b14634d6e6"
  },
  "customer_name": "test user",
  "phone_number": "0973605900",
  "email": "haudaoquang5@gmail.com",
  "address": "Lương Tài, Văn Lâm, Hưng Yên",
  "appointment_date": {
    "$date": "2025-05-18T00:00:00.000Z"
  },
  "timeslot": {
    "$oid": "68286a2b0fe24f52ff8853da"
  },
  "order_status": "Pending",
  "pet_info": {
    "pet_name": "Mực",
    "species": "Mèo",
    "breed": "Cam",
    "age": 1,
    "weight": 2,
    "notes": "a"
  },
  "cancel_reason": "null",
  "createdAt": {
    "$date": "2025-05-17T11:57:09.878Z"
  },
  "updatedAt": {
    "$date": "2025-05-17T11:57:09.878Z"
  },
  "__v": 0
},
{
  "_id": {
    "$oid": "68287a8d1a7412368ad1f019"
  },
  "userId": {
    "$oid": "6825ee32eed18af919a0ed64"
  },
  "service_type": {
    "$oid": "668959f11561a7b14634d6e6"
  },
  "customer_name": "Đào Quang Hậu",
  "phone_number": "0973605900",
  "email": "daoquanghau2003@gmail.com",
  "address": "Lương Tài, Văn Lâm, Hưng Yên",
  "appointment_date": {
    "$date": "2025-05-25T00:00:00.000Z"
  },
  "timeslot": {
    "$oid": "68286a2b0fe24f52ff8853da"
  },
  "order_status": "Pending",
  "pet_info": {
    "pet_name": "Meow",
    "species": "Mèo",
    "breed": "Lai",
    "age": 11,
    "weight": 12,
    "notes": ""
  },
  "cancel_reason": "null",
  "createdAt": {
    "$date": "2025-05-17T12:01:17.124Z"
  },
  "updatedAt": {
    "$date": "2025-05-17T12:01:17.124Z"
  },
  "__v": 0
},
{
  "_id": {
    "$oid": "68287a9a1a7412368ad1f023"
  },
  "userId": {
    "$oid": "6825ee32eed18af919a0ed64"
  },
  "service_type": {
    "$oid": "682432ed79206bf9c099f161"
  },
  "customer_name": "test user",
  "phone_number": "0973605900",
  "email": "haudaoquang5@gmail.com",
  "address": "Lương Tài, Văn Lâm, Hưng Yên",
  "appointment_date": {
    "$date": "2025-05-20T00:00:00.000Z"
  },
  "timeslot": {
    "$oid": "68286a2b0fe24f52ff8853da"
  },
  "order_status": "Pending",
  "pet_info": {
    "pet_name": "chó 2",
    "species": "chó",
    "breed": "husky",
    "age": 3,
    "weight": 5,
    "notes": ""
  },
  "cancel_reason": "null",
  "createdAt": {
    "$date": "2025-05-17T12:01:30.443Z"
  },
  "updatedAt": {
    "$date": "2025-05-17T12:01:30.443Z"
  },
  "__v": 0
},
{
  "_id": {
    "$oid": "68288d126cb337b6e0178390"
  },
  "userId": {
    "$oid": "682738a3f2cdeecc95b469de"
  },
  "service_type": {
    "$oid": "682432ed79206bf9c099f161"
  },
  "customer_name": "Đào Quang Hậu",
  "phone_number": "0973605900",
  "email": "daoquanghau2003@gmail.com",
  "address": "Lương Tài, Văn Lâm, Hưng Yên",
  "appointment_date": {
    "$date": "2025-05-18T00:00:00.000Z"
  },
  "timeslot": {
    "$oid": "68286a2b0fe24f52ff8853da"
  },
  "order_status": "Pending",
  "pet_info": {
    "pet_name": "test 2",
    "species": "mèo",
    "breed": "anh",
    "age": 1,
    "weight": 12,
    "notes": ""
  },
  "cancel_reason": "null",
  "createdAt": {
    "$date": "2025-05-17T13:20:18.847Z"
  },
  "updatedAt": {
    "$date": "2025-05-17T13:20:18.847Z"
  },
  "__v": 0
}]